{"boss": {"num": 837, "name": "Fenriloogamon TK", "hp": 527450000, "max_hp": 528000000, "start": 5000000.0, "end": 5691200.0}, "board": {"ana": {"damage": 500000, "ts": 5000000.0}, "bob": {"damage": 50000, "ts": 5000000.0}}, "history": [{"id": "4691200", "boss_name": "Brigadramon", "num": 785, "defeated": true, "ended": 4000000.0, "board": {"first": {"damage": 2000000, "ts": 4000000.0}}}, {"id": "4000009", "boss_name": "Cherubimon_Virtue", "num": 798, "defeated": false, "ended": 4000010.0, "board": {"second": {"damage": 100000, "ts": 4000010.0}}}, {"id": "4691210", "boss_name": "DORUgoramon", "num": 804, "defeated": false, "ended": 5000000.0, "board": {}}, {"id": "5691200", "boss_name": "Plesiomon", "num": 926, "defeated": true, "ended": 4000000.0, "board": {"ana": {"damage": 500000, "ts": 5000000.0}, "bob": {"damage": 50000, "ts": 5000000.0}, "joel": {"damage": 6100000, "ts": 3086400.0}, "first": {"damage": 2000000, "ts": 4000000.0}}}, {"id": "4691200", "boss_name": "Gankoomon_X", "num": 843, "defeated": false, "ended": 5000000.0, "board": {}}], "claimed": {"4691200": ["first"]}, "attempts": {"joel": {"date": "1970-02-05", "left": 2}, "first": {"date": "1970-02-16", "left": 1}, "second": {"date": "1970-02-16", "left": 2}, "ana": {"date": "1970-02-27", "left": 1}, "bob": {"date": "1970-02-27", "left": 1}}}